cf_deploy/__init__.py
cf_deploy/main.py
cf_deploy/models.py
cf_deploy/utils/__init__.py
cf_deploy/utils/logging.py
cf_deploy-0.1.57.dist-info/METADATA
cf_deploy-0.1.57.dist-info/WHEEL
cf_deploy-0.1.57.dist-info/entry_points.txt
cf_deploy-0.1.57.dist-info/RECORD
