Metadata-Version: 2.4
Name: cf-deploy
Version: 0.1.57
Summary: A package to automate CloudFormation deployments
License: MIT
Author: Bart Machielsen
Author-email: bartmachielsen@gmail.com
Requires-Python: >=3.9,<4.0
Classifier: License :: OSI Approved :: MIT License
Classifier: Programming Language :: Python :: 3
Classifier: Programming Language :: Python :: 3.9
Classifier: Programming Language :: Python :: 3.10
Classifier: Programming Language :: Python :: 3.11
Classifier: Programming Language :: Python :: 3.12
Classifier: Programming Language :: Python :: 3.13
Classifier: Programming Language :: Python :: 3.14
Requires-Dist: PyYAML (>=6.0.1,<7.0.0)
Requires-Dist: boto3 (>=1.20.0,<2.0.0)
Requires-Dist: colorama (>=0.4.4,<0.5.0)
Requires-Dist: deepmerge (>=0.3.0,<0.4.0)
Requires-Dist: pydantic (>=2.11.3,<3.0.0)
Requires-Dist: structlog (>=21.5.0,<22.0.0)
Requires-Dist: tqdm (>=4.65.0,<5.0.0)
